{
  "usuarios": {
    "victor.endo": {
      "senha": "8c6976e5b5410415bde908bd4dee15dfb167a9c873fc4bb8a81f6f2ab448a918",
      "nivel": "admin",
      "nome": "Victor Endo",
      "criado_em": "2026-02-25 14:00:00"
    },
    "ponto.operacional": {
      "senha": "8d969eef6ecad3c29a3a629280e686cf0c3f5d5a86aff3ca12020c923adc6c92",
      "nivel": "usuario",
      "nome": "Ponto Operacional",
      "criado_em": "2026-02-25 16:08:26"
    },
    "carlos.oliveira": {
      "senha": "ac9c2c34c9f7ad52528c3422af40a66e2e24aaf2a727831255413c9470158984",
      "nivel": "usuario",
      "nome": "Carlos Oliveira",
      "criado_em": "2026-02-26 15:59:09"
    },
    "emerson.pimentel": {
      "senha": "db56f2135ebada812da647340eba07d48930a3f985bd3c973b4de0958db222db",
      "nivel": "usuario",
      "nome": "Emerson Pimentel",
      "criado_em": "2026-02-27 16:37:08"
    }
  }
}